blitzbuffers/__init__.py
blitzbuffers/__main__.py
blitzbuffers/arg_util.py
blitzbuffers/languages.py
blitzbuffers/output_builder.py
blitzbuffers/parsing.py
blitzbuffers/shared.py
blitzbuffers/cpp/__init__.py
blitzbuffers/cpp/blitzbuffers.hpp
blitzbuffers/cpp/common.py
blitzbuffers/cpp/enum.py
blitzbuffers/cpp/generate.py
blitzbuffers/cpp/prepare.py
blitzbuffers/cpp/struct.py
blitzbuffers/cpp/tagged_union.py
blitzbuffers/printer/__init__.py
blitzbuffers/printer/printer.py
blitzbuffers/rust/__init__.py
blitzbuffers/rust/blitzbuffers.rs
blitzbuffers/rust/common.py
blitzbuffers/rust/enum.py
blitzbuffers/rust/generate.py
blitzbuffers/rust/prepare.py
blitzbuffers/rust/struct.py
blitzbuffers/rust/tagged_union.py
blitzbuffers-0.3.0.dist-info/METADATA
blitzbuffers-0.3.0.dist-info/WHEEL
blitzbuffers-0.3.0.dist-info/licenses/LICENSE
blitzbuffers-0.3.0.dist-info/RECORD
