Metadata-Version: 2.4
Name: blitzbuffers
Version: 0.3.0
Summary: Code-generation library and tool for the BlitzBuffers serialization format
Project-URL: Homepage, https://github.com/InoUno/blitzbuffers
Project-URL: Issues, https://github.com/InoUno/blitzbuffers/issues
Author-email: InoUno <inoiown@gmail.com>
License-Expression: MIT
License-File: LICENSE
Classifier: License :: OSI Approved :: MIT License
Classifier: Operating System :: OS Independent
Classifier: Programming Language :: Python :: 3
Requires-Python: >=3.9
Requires-Dist: lark
